gmlsnets_pytorch/__init__.py
gmlsnets_pytorch/dataset.py
gmlsnets_pytorch/nn.py
gmlsnets_pytorch/util.py
gmlsnets_pytorch/vis.py
gmlsnets_pytorch-1.0.0.dist-info/LICENSE.txt
gmlsnets_pytorch-1.0.0.dist-info/METADATA
gmlsnets_pytorch-1.0.0.dist-info/WHEEL
gmlsnets_pytorch-1.0.0.dist-info/top_level.txt
gmlsnets_pytorch-1.0.0.dist-info/RECORD
