Metadata-Version: 2.1
Name: gmlsnets-pytorch
Version: 1.0.0
Summary: Implementation of GMLS-Nets in PyTorch.
Home-page: http://atzberger.org/
Author: Ben J. Gross and Paul J. Atzberger
Author-email: atzberg@gmail.com
License: UNKNOWN
Platform: UNKNOWN
Classifier: Programming Language :: Python :: 3
Classifier: License :: OSI Approved :: BSD License
Classifier: Operating System :: OS Independent
Requires-Python: >=3.6
